README
setup.py
tweetstream/__init__.py
tweetstream.egg-info/PKG-INFO
tweetstream.egg-info/SOURCES.txt
tweetstream.egg-info/dependency_links.txt
tweetstream.egg-info/not-zip-safe
tweetstream.egg-info/top_level.txt