Metadata-Version: 1.0
Name: tweetstream
Version: 0.3
Summary: Simple Twitter streaming API access
Home-page: http://bitbucket.org/runeh/tweetstream/
Author: Rune Halvorsen
Author-email: runefh@gmail.com
License: BSD
Keywords: twitter
Platform: any
Classifier: License :: OSI Approved :: BSD License
Classifier: Intended Audience :: Developers
